pycorreios3/CEP.py
pycorreios3/__init__.py
pycorreios3/calc_preco_prazo.py
pycorreios3/cartao_postagem.py
pycorreios3/correios_webservice_client.py
pycorreios3/credenciais.py
pycorreios3/servicos.py
pycorreios3/sigepweb.py
pycorreios3/sro.py
pycorreios3/volume.py
pycorreios3-1.2.2.dist-info/LICENSE
pycorreios3-1.2.2.dist-info/WHEEL
pycorreios3-1.2.2.dist-info/METADATA
pycorreios3-1.2.2.dist-info/RECORD
